threadmem/__init__.py
threadmem/auth/default.py
threadmem/auth/key.py
threadmem/auth/provider.py
threadmem/auth/transport.py
threadmem/config.py
threadmem/db/conn.py
threadmem/db/models.py
threadmem/env.py
threadmem/img.py
threadmem/role.py
threadmem/server/app.py
threadmem/server/models.py
threadmem/server/routes.py
threadmem/thread.py
threadmem-0.2.39.dist-info/LICENSE
threadmem-0.2.39.dist-info/METADATA
threadmem-0.2.39.dist-info/WHEEL
threadmem-0.2.39.dist-info/entry_points.txt
threadmem-0.2.39.dist-info/RECORD
