Metadata-Version: 2.1
Name: threadmem
Version: 0.2.39
Summary: Thread memory for AI agents
License: MIT
Author: Patrick Barker
Author-email: patrickbarkerco@gmail.com
Requires-Python: >=3.10,<4.0
Classifier: License :: OSI Approved :: MIT License
Classifier: Programming Language :: Python :: 3
Classifier: Programming Language :: Python :: 3.10
Classifier: Programming Language :: Python :: 3.11
Classifier: Programming Language :: Python :: 3.12
Requires-Dist: fastapi[all] (>=0.109,<0.110)
Requires-Dist: google-cloud-storage (>=2.17.0,<3.0.0)
Requires-Dist: pillow (>=10.3.0,<11.0.0)
Requires-Dist: pydantic (>=2.6.3,<3.0.0)
Requires-Dist: requests (>=2.31.0,<3.0.0)
Requires-Dist: shortuuid (>=1.0.13,<2.0.0)
Requires-Dist: sqlalchemy (>=2.0.27,<3.0.0)
